[
  {
    "slug": "yada-yada-yada",
    "title": "Laravel config explained",
    "description": "I was confused about this, because when I copy-paste my text it's already have some spaces before it.\nNow I try shift+tab in my editor and make indent again and it's work fine right now.\nSpend some hours for this, thank you again!",
    "publishedAt": "2022-12-03T19:29:35.853Z"
  },
  {
    "slug": "laravel-config-explained",
    "title": "Laravel config explained easily",
    "description": "I was confused about this, because when I copy-paste my text it's already have some spaces before it.\nNow I try shift+tab in my editor and make indent again and it's work fine right now.\nSpend some hours for this, thank you again!",
    "publishedAt": "2022-12-04T19:42:00.516Z"
  }
]